configurable_argparse.py
configurable_argparse_DavidRodriguezSoaresCUI-0.0.2.dist-info/LICENSE
configurable_argparse_DavidRodriguezSoaresCUI-0.0.2.dist-info/METADATA
configurable_argparse_DavidRodriguezSoaresCUI-0.0.2.dist-info/WHEEL
configurable_argparse_DavidRodriguezSoaresCUI-0.0.2.dist-info/top_level.txt
configurable_argparse_DavidRodriguezSoaresCUI-0.0.2.dist-info/RECORD
