Metadata-Version: 2.1
Name: configurable-argparse-DavidRodriguezSoaresCUI
Version: 0.0.2
Summary: Argparse-based way of CLI argument handling boosted by YAML reusable configurations
Author-email: DavidRodriguezSoaresCUI <fireblaze904+argparse@gmail.com>
License: CC0 1.0 Universal
Project-URL: Homepage, https://github.com/DavidRodriguezSoaresCUI/configurable_argparse
Project-URL: Bug Tracker, https://github.com/DavidRodriguezSoaresCUI/configurable_argparse/issues
Classifier: Development Status :: 3 - Alpha
Classifier: Programming Language :: Python :: 3
Classifier: License :: CC0 1.0 Universal (CC0 1.0) Public Domain Dedication
Classifier: Operating System :: OS Independent
Requires-Python: >=3.7
License-File: LICENSE
Requires-Dist: DRSlib-DavidRodriguezSoaresCUI (>=0.7.0)
